{
  "0.0": [
    [
      1280,
      214
    ],
    [
      0,
      223
    ],
    [
      0,
      605
    ],
    [
      1280,
      613
    ],
    [
      1280,
      214
    ]
  ],
  "0.1": [
    [
      1280,
      114
    ],
    [
      0,
      157
    ],
    [
      0,
      602
    ],
    [
      1280,
      603
    ],
    [
      1280,
      114
    ]
  ],
  "0.2": [
    [
      1280,
      162
    ],
    [
      0,
      167
    ],
    [
      0,
      598
    ],
    [
      1280,
      603
    ],
    [
      1280,
      162
    ]
  ],
  "0.30000000000000004": [
    [
      1280,
      166
    ],
    [
      0,
      170
    ],
    [
      0,
      645
    ],
    [
      1280,
      621
    ],
    [
      1280,
      166
    ]
  ],
  "0.4": [
    [
      1280,
      238
    ],
    [
      0,
      243
    ],
    [
      0,
      633
    ],
    [
      1280,
      646
    ],
    [
      1280,
      238
    ]
  ],
  "0.5": [
    [
      1280,
      190
    ],
    [
      0,
      221
    ],
    [
      0,
      631
    ],
    [
      1280,
      623
    ],
    [
      1280,
      190
    ]
  ],
  "0.6000000000000001": [
    [
      1280,
      127
    ],
    [
      0,
      166
    ],
    [
      0,
      636
    ],
    [
      1280,
      611
    ],
    [
      1280,
      127
    ]
  ],
  "0.7000000000000001": [
    [
      1280,
      170
    ],
    [
      0,
      166
    ],
    [
      0,
      652
    ],
    [
      1280,
      633
    ],
    [
      1280,
      170
    ]
  ],
  "0.8": [
    [
      1280,
      148
    ],
    [
      0,
      178
    ],
    [
      0,
      631
    ],
    [
      1280,
      614
    ],
    [
      1280,
      148
    ]
  ],
  "0.9": [
    [
      1280,
      201
    ],
    [
      0,
      172
    ],
    [
      0,
      640
    ],
    [
      1280,
      602
    ],
    [
      1280,
      201
    ]
  ],
  "1.0": [
    [
      1280,
      210
    ],
    [
      0,
      173
    ],
    [
      0,
      642
    ],
    [
      1280,
      623
    ],
    [
      1280,
      210
    ]
  ],
  "1.1": [
    [
      1280,
      184
    ],
    [
      0,
      206
    ],
    [
      0,
      640
    ],
    [
      1280,
      620
    ],
    [
      1280,
      184
    ]
  ],
  "1.2000000000000002": [
    [
      1280,
      157
    ],
    [
      0,
      157
    ],
    [
      0,
      643
    ],
    [
      1280,
      608
    ],
    [
      1280,
      157
    ]
  ],
  "1.3": [
    [
      1280,
      124
    ],
    [
      0,
      145
    ],
    [
      0,
      632
    ],
    [
      1280,
      612
    ],
    [
      1280,
      124
    ]
  ],
  "1.4000000000000001": [
    [
      1280,
      131
    ],
    [
      0,
      150
    ],
    [
      0,
      625
    ],
    [
      1280,
      615
    ],
    [
      1280,
      131
    ]
  ],
  "1.5": [
    [
      1280,
      153
    ],
    [
      0,
      139
    ],
    [
      0,
      642
    ],
    [
      1280,
      612
    ],
    [
      1280,
      153
    ]
  ],
  "1.6": [
    [
      1280,
      197
    ],
    [
      0,
      183
    ],
    [
      0,
      639
    ],
    [
      1280,
      623
    ],
    [
      1280,
      197
    ]
  ],
  "1.7000000000000002": [
    [
      1280,
      204
    ],
    [
      0,
      244
    ],
    [
      0,
      645
    ],
    [
      1280,
      658
    ],
    [
      1280,
      204
    ]
  ],
  "1.8": [
    [
      1280,
      118
    ],
    [
      0,
      105
    ],
    [
      0,
      635
    ],
    [
      1280,
      622
    ],
    [
      1280,
      118
    ]
  ],
  "1.9000000000000001": [
    [
      1280,
      173
    ],
    [
      0,
      182
    ],
    [
      0,
      628
    ],
    [
      1280,
      640
    ],
    [
      1280,
      173
    ]
  ],
  "2.0": [
    [
      1280,
      175
    ],
    [
      0,
      141
    ],
    [
      0,
      646
    ],
    [
      1280,
      630
    ],
    [
      1280,
      175
    ]
  ],
  "2.1": [
    [
      1280,
      242
    ],
    [
      0,
      233
    ],
    [
      0,
      637
    ],
    [
      1280,
      631
    ],
    [
      1280,
      242
    ]
  ],
  "2.2": [
    [
      1280,
      148
    ],
    [
      0,
      240
    ],
    [
      0,
      640
    ],
    [
      1280,
      665
    ],
    [
      1280,
      148
    ]
  ],
  "2.3000000000000003": [
    [
      1280,
      224
    ],
    [
      0,
      214
    ],
    [
      0,
      636
    ],
    [
      1280,
      627
    ],
    [
      1280,
      224
    ]
  ],
  "2.4000000000000004": [
    [
      1280,
      139
    ],
    [
      0,
      143
    ],
    [
      0,
      633
    ],
    [
      1280,
      636
    ],
    [
      1280,
      139
    ]
  ],
  "2.5": [
    [
      1280,
      152
    ],
    [
      0,
      146
    ],
    [
      0,
      628
    ],
    [
      1280,
      619
    ],
    [
      1280,
      152
    ]
  ],
  "2.6": [
    [
      1280,
      139
    ],
    [
      0,
      140
    ],
    [
      0,
      639
    ],
    [
      1280,
      630
    ],
    [
      1280,
      139
    ]
  ],
  "2.7": [
    [
      1280,
      143
    ],
    [
      0,
      155
    ],
    [
      0,
      643
    ],
    [
      1280,
      633
    ],
    [
      1280,
      143
    ]
  ],
  "2.8000000000000003": [
    [
      1280,
      164
    ],
    [
      0,
      122
    ],
    [
      0,
      649
    ],
    [
      1280,
      614
    ],
    [
      1280,
      164
    ]
  ],
  "2.9000000000000004": [
    [
      1280,
      157
    ],
    [
      0,
      162
    ],
    [
      0,
      639
    ],
    [
      1280,
      629
    ],
    [
      1280,
      157
    ]
  ],
  "3.0": [
    [
      1280,
      183
    ],
    [
      0,
      173
    ],
    [
      0,
      637
    ],
    [
      1280,
      642
    ],
    [
      1280,
      183
    ]
  ],
  "3.1": [
    [
      1280,
      132
    ],
    [
      0,
      160
    ],
    [
      0,
      654
    ],
    [
      1280,
      644
    ],
    [
      1280,
      132
    ]
  ],
  "3.2": [
    [
      1280,
      157
    ],
    [
      0,
      126
    ],
    [
      0,
      657
    ],
    [
      1280,
      647
    ],
    [
      1280,
      157
    ]
  ],
  "3.3000000000000003": [
    [
      1280,
      160
    ],
    [
      0,
      176
    ],
    [
      0,
      641
    ],
    [
      1280,
      643
    ],
    [
      1280,
      160
    ]
  ],
  "3.4000000000000004": [
    [
      1280,
      177
    ],
    [
      0,
      175
    ],
    [
      0,
      633
    ],
    [
      1280,
      647
    ],
    [
      1280,
      177
    ]
  ],
  "3.5": [
    [
      1280,
      132
    ],
    [
      0,
      106
    ],
    [
      0,
      643
    ],
    [
      1280,
      638
    ],
    [
      1280,
      132
    ]
  ],
  "3.6": [
    [
      1280,
      200
    ],
    [
      0,
      175
    ],
    [
      0,
      645
    ],
    [
      1280,
      646
    ],
    [
      1280,
      200
    ]
  ],
  "3.7": [
    [
      1280,
      150
    ],
    [
      0,
      132
    ],
    [
      0,
      626
    ],
    [
      1280,
      650
    ],
    [
      1280,
      150
    ]
  ],
  "3.8000000000000003": [
    [
      1280,
      168
    ],
    [
      0,
      169
    ],
    [
      0,
      633
    ],
    [
      1280,
      663
    ],
    [
      1280,
      168
    ]
  ],
  "3.9000000000000004": [
    [
      1280,
      218
    ],
    [
      0,
      169
    ],
    [
      0,
      637
    ],
    [
      1280,
      655
    ],
    [
      1280,
      218
    ]
  ],
  "4.0": [
    [
      1280,
      131
    ],
    [
      0,
      141
    ],
    [
      0,
      620
    ],
    [
      1280,
      639
    ],
    [
      1280,
      131
    ]
  ],
  "4.1000000000000005": [
    [
      1280,
      237
    ],
    [
      0,
      238
    ],
    [
      0,
      604
    ],
    [
      1280,
      640
    ],
    [
      1280,
      237
    ]
  ],
  "4.2": [
    [
      1280,
      168
    ],
    [
      0,
      168
    ],
    [
      0,
      628
    ],
    [
      1280,
      665
    ],
    [
      1280,
      168
    ]
  ],
  "4.3": [
    [
      1280,
      128
    ],
    [
      0,
      126
    ],
    [
      0,
      610
    ],
    [
      1280,
      644
    ],
    [
      1280,
      128
    ]
  ],
  "4.4": [
    [
      1280,
      193
    ],
    [
      0,
      165
    ],
    [
      0,
      625
    ],
    [
      1280,
      653
    ],
    [
      1280,
      193
    ]
  ],
  "4.5": [
    [
      1280,
      178
    ],
    [
      0,
      131
    ],
    [
      0,
      606
    ],
    [
      1280,
      629
    ],
    [
      1280,
      178
    ]
  ],
  "4.6000000000000005": [
    [
      1280,
      155
    ],
    [
      0,
      153
    ],
    [
      0,
      619
    ],
    [
      1280,
      648
    ],
    [
      1280,
      155
    ]
  ],
  "4.7": [
    [
      1280,
      246
    ],
    [
      0,
      205
    ],
    [
      0,
      638
    ],
    [
      1280,
      661
    ],
    [
      1280,
      246
    ]
  ],
  "4.800000000000001": [
    [
      1280,
      137
    ],
    [
      0,
      165
    ],
    [
      0,
      616
    ],
    [
      1280,
      658
    ],
    [
      1280,
      137
    ]
  ],
  "4.9": [
    [
      1280,
      142
    ],
    [
      0,
      160
    ],
    [
      0,
      600
    ],
    [
      1280,
      642
    ],
    [
      1280,
      142
    ]
  ],
  "5.0": [
    [
      1280,
      185
    ],
    [
      0,
      153
    ],
    [
      0,
      611
    ],
    [
      1280,
      642
    ],
    [
      1280,
      185
    ]
  ],
  "5.1000000000000005": [
    [
      1280,
      168
    ],
    [
      0,
      147
    ],
    [
      0,
      610
    ],
    [
      1280,
      637
    ],
    [
      1280,
      168
    ]
  ],
  "5.2": [
    [
      1280,
      176
    ],
    [
      0,
      131
    ],
    [
      0,
      604
    ],
    [
      1280,
      649
    ],
    [
      1280,
      176
    ]
  ],
  "5.300000000000001": [
    [
      1280,
      99
    ],
    [
      0,
      141
    ],
    [
      0,
      588
    ],
    [
      1280,
      634
    ],
    [
      1280,
      99
    ]
  ],
  "5.4": [
    [
      1280,
      154
    ],
    [
      0,
      172
    ],
    [
      0,
      602
    ],
    [
      1280,
      639
    ],
    [
      1280,
      154
    ]
  ],
  "5.5": [
    [
      1280,
      162
    ],
    [
      0,
      133
    ],
    [
      0,
      592
    ],
    [
      1280,
      634
    ],
    [
      1280,
      162
    ]
  ],
  "5.6000000000000005": [
    [
      1280,
      155
    ],
    [
      0,
      99
    ],
    [
      0,
      585
    ],
    [
      1280,
      621
    ],
    [
      1280,
      155
    ]
  ],
  "5.7": [
    [
      1280,
      205
    ],
    [
      0,
      175
    ],
    [
      0,
      574
    ],
    [
      1280,
      623
    ],
    [
      1280,
      205
    ]
  ],
  "5.800000000000001": [
    [
      1280,
      146
    ],
    [
      45,
      179
    ],
    [
      0,
      195
    ],
    [
      0,
      577
    ],
    [
      1280,
      620
    ],
    [
      1280,
      146
    ]
  ],
  "5.9": [
    [
      1280,
      107
    ],
    [
      4,
      124
    ],
    [
      0,
      126
    ],
    [
      0,
      569
    ],
    [
      1280,
      623
    ],
    [
      1280,
      107
    ]
  ],
  "6.0": [
    [
      1280,
      149
    ],
    [
      0,
      127
    ],
    [
      0,
      583
    ],
    [
      1280,
      640
    ],
    [
      1280,
      149
    ]
  ],
  "6.1000000000000005": [
    [
      1280,
      171
    ],
    [
      45,
      174
    ],
    [
      0,
      189
    ],
    [
      0,
      588
    ],
    [
      1280,
      641
    ],
    [
      1280,
      171
    ]
  ],
  "6.2": [
    [
      1280,
      205
    ],
    [
      0,
      166
    ],
    [
      0,
      574
    ],
    [
      1280,
      615
    ],
    [
      1280,
      205
    ]
  ],
  "6.300000000000001": [
    [
      1280,
      134
    ],
    [
      34,
      110
    ],
    [
      0,
      123
    ],
    [
      0,
      560
    ],
    [
      1280,
      623
    ],
    [
      1280,
      134
    ]
  ],
  "6.4": [
    [
      1280,
      142
    ],
    [
      19,
      107
    ],
    [
      0,
      114
    ],
    [
      0,
      556
    ],
    [
      1280,
      614
    ],
    [
      1280,
      142
    ]
  ],
  "6.5": [
    [
      1280,
      103
    ],
    [
      37,
      110
    ],
    [
      0,
      128
    ],
    [
      0,
      551
    ],
    [
      1280,
      600
    ],
    [
      1280,
      103
    ]
  ],
  "6.6000000000000005": [
    [
      1280,
      186
    ],
    [
      41,
      190
    ],
    [
      0,
      204
    ],
    [
      0,
      578
    ],
    [
      1280,
      649
    ],
    [
      1280,
      186
    ]
  ],
  "6.7": [
    [
      1280,
      126
    ],
    [
      58,
      101
    ],
    [
      0,
      126
    ],
    [
      0,
      547
    ],
    [
      1280,
      616
    ],
    [
      1280,
      126
    ]
  ],
  "6.800000000000001": [
    [
      1280,
      142
    ],
    [
      46,
      113
    ],
    [
      0,
      132
    ],
    [
      0,
      541
    ],
    [
      1280,
      616
    ],
    [
      1280,
      142
    ]
  ],
  "6.9": [
    [
      1280,
      179
    ],
    [
      99,
      176
    ],
    [
      0,
      209
    ],
    [
      0,
      552
    ],
    [
      1280,
      618
    ],
    [
      1280,
      179
    ]
  ],
  "7.0": [
    [
      1280,
      173
    ],
    [
      21,
      140
    ],
    [
      0,
      148
    ],
    [
      0,
      561
    ],
    [
      1280,
      621
    ],
    [
      1280,
      173
    ]
  ],
  "7.1000000000000005": [
    [
      1280,
      151
    ],
    [
      77,
      126
    ],
    [
      0,
      156
    ],
    [
      0,
      536
    ],
    [
      1280,
      621
    ],
    [
      1280,
      151
    ]
  ],
  "7.2": [
    [
      1280,
      125
    ],
    [
      93,
      140
    ],
    [
      0,
      179
    ],
    [
      0,
      535
    ],
    [
      1280,
      590
    ],
    [
      1280,
      125
    ]
  ],
  "7.300000000000001": [
    [
      1280,
      159
    ],
    [
      71,
      154
    ],
    [
      0,
      183
    ],
    [
      0,
      537
    ],
    [
      1280,
      618
    ],
    [
      1280,
      159
    ]
  ],
  "7.4": [
    [
      1280,
      129
    ],
    [
      83,
      128
    ],
    [
      0,
      163
    ],
    [
      0,
      530
    ],
    [
      1280,
      593
    ],
    [
      1280,
      129
    ]
  ],
  "7.5": [
    [
      1280,
      155
    ],
    [
      49,
      115
    ],
    [
      0,
      133
    ],
    [
      0,
      525
    ],
    [
      1280,
      602
    ],
    [
      1280,
      155
    ]
  ],
  "7.6000000000000005": [
    [
      1280,
      216
    ],
    [
      106,
      184
    ],
    [
      0,
      212
    ],
    [
      0,
      540
    ],
    [
      1280,
      606
    ],
    [
      1280,
      216
    ]
  ],
  "7.7": [
    [
      1280,
      153
    ],
    [
      110,
      147
    ],
    [
      0,
      191
    ],
    [
      0,
      531
    ],
    [
      1280,
      588
    ],
    [
      1280,
      153
    ]
  ],
  "7.800000000000001": [
    [
      1280,
      191
    ],
    [
      64,
      174
    ],
    [
      0,
      196
    ],
    [
      0,
      553
    ],
    [
      1280,
      613
    ],
    [
      1280,
      191
    ]
  ],
  "7.9": [
    [
      1280,
      187
    ],
    [
      105,
      146
    ],
    [
      0,
      180
    ],
    [
      0,
      535
    ],
    [
      1280,
      595
    ],
    [
      1280,
      187
    ]
  ],
  "8.0": [
    [
      1280,
      220
    ],
    [
      106,
      211
    ],
    [
      0,
      240
    ],
    [
      0,
      531
    ],
    [
      1280,
      600
    ],
    [
      1280,
      220
    ]
  ],
  "8.1": [
    [
      1280,
      156
    ],
    [
      77,
      160
    ],
    [
      0,
      192
    ],
    [
      0,
      535
    ],
    [
      1280,
      593
    ],
    [
      1280,
      156
    ]
  ],
  "8.200000000000001": [
    [
      1280,
      245
    ],
    [
      173,
      240
    ],
    [
      0,
      277
    ],
    [
      0,
      530
    ],
    [
      1280,
      590
    ],
    [
      1280,
      245
    ]
  ],
  "8.3": [
    [
      1280,
      125
    ],
    [
      126,
      166
    ],
    [
      0,
      222
    ],
    [
      0,
      532
    ],
    [
      1280,
      599
    ],
    [
      1280,
      125
    ]
  ],
  "8.4": [
    [
      1280,
      201
    ],
    [
      119,
      217
    ],
    [
      0,
      251
    ],
    [
      0,
      531
    ],
    [
      1280,
      602
    ],
    [
      1280,
      201
    ]
  ],
  "8.5": [
    [
      1280,
      183
    ],
    [
      143,
      179
    ],
    [
      0,
      227
    ],
    [
      0,
      523
    ],
    [
      1280,
      587
    ],
    [
      1280,
      183
    ]
  ],
  "8.6": [
    [
      1280,
      211
    ],
    [
      125,
      226
    ],
    [
      0,
      261
    ],
    [
      0,
      558
    ],
    [
      1280,
      615
    ],
    [
      1280,
      211
    ]
  ],
  "8.700000000000001": [
    [
      1280,
      197
    ],
    [
      143,
      194
    ],
    [
      0,
      240
    ],
    [
      0,
      529
    ],
    [
      1280,
      584
    ],
    [
      1280,
      197
    ]
  ],
  "8.8": [
    [
      1280,
      176
    ],
    [
      108,
      156
    ],
    [
      0,
      196
    ],
    [
      0,
      530
    ],
    [
      1280,
      575
    ],
    [
      1280,
      176
    ]
  ],
  "8.9": [
    [
      1280,
      193
    ],
    [
      82,
      155
    ],
    [
      0,
      182
    ],
    [
      0,
      534
    ],
    [
      1280,
      601
    ],
    [
      1280,
      193
    ]
  ],
  "9.0": [
    [
      1280,
      177
    ],
    [
      81,
      144
    ],
    [
      0,
      173
    ],
    [
      0,
      536
    ],
    [
      1280,
      596
    ],
    [
      1280,
      177
    ]
  ],
  "9.1": [
    [
      1280,
      210
    ],
    [
      68,
      135
    ],
    [
      0,
      154
    ],
    [
      0,
      533
    ],
    [
      1280,
      593
    ],
    [
      1280,
      210
    ]
  ],
  "9.200000000000001": [
    [
      1280,
      185
    ],
    [
      115,
      146
    ],
    [
      0,
      183
    ],
    [
      0,
      529
    ],
    [
      1280,
      584
    ],
    [
      1280,
      185
    ]
  ],
  "9.3": [
    [
      1280,
      190
    ],
    [
      98,
      158
    ],
    [
      0,
      194
    ],
    [
      0,
      542
    ],
    [
      1280,
      591
    ],
    [
      1280,
      190
    ]
  ],
  "9.4": [
    [
      1280,
      197
    ],
    [
      179,
      237
    ],
    [
      0,
      295
    ],
    [
      0,
      545
    ],
    [
      1280,
      607
    ],
    [
      1280,
      197
    ]
  ],
  "9.5": [
    [
      1280,
      151
    ],
    [
      100,
      164
    ],
    [
      0,
      204
    ],
    [
      0,
      541
    ],
    [
      1280,
      586
    ],
    [
      1280,
      151
    ]
  ],
  "9.600000000000001": [
    [
      1280,
      193
    ],
    [
      41,
      141
    ],
    [
      0,
      155
    ],
    [
      0,
      542
    ],
    [
      1280,
      596
    ],
    [
      1280,
      193
    ]
  ],
  "9.700000000000001": [
    [
      1280,
      210
    ],
    [
      132,
      192
    ],
    [
      0,
      232
    ],
    [
      0,
      539
    ],
    [
      1280,
      600
    ],
    [
      1280,
      210
    ]
  ],
  "9.8": [
    [
      1280,
      194
    ],
    [
      162,
      227
    ],
    [
      0,
      281
    ],
    [
      0,
      538
    ],
    [
      1280,
      610
    ],
    [
      1280,
      194
    ]
  ],
  "9.9": [
    [
      1280,
      260
    ],
    [
      91,
      236
    ],
    [
      0,
      253
    ],
    [
      0,
      547
    ],
    [
      1280,
      593
    ],
    [
      1280,
      260
    ]
  ],
  "10.0": [
    [
      1280,
      217
    ],
    [
      8,
      180
    ],
    [
      0,
      182
    ],
    [
      0,
      561
    ],
    [
      1280,
      603
    ],
    [
      1280,
      217
    ]
  ],
  "10.100000000000001": [
    [
      1280,
      105
    ],
    [
      63,
      157
    ],
    [
      0,
      187
    ],
    [
      0,
      537
    ],
    [
      1280,
      588
    ],
    [
      1280,
      105
    ]
  ],
  "10.200000000000001": [
    [
      1280,
      229
    ],
    [
      59,
      235
    ],
    [
      0,
      253
    ],
    [
      0,
      559
    ],
    [
      1280,
      615
    ],
    [
      1280,
      229
    ]
  ],
  "10.3": [
    [
      1280,
      173
    ],
    [
      74,
      221
    ],
    [
      0,
      248
    ],
    [
      0,
      555
    ],
    [
      1280,
      611
    ],
    [
      1280,
      173
    ]
  ],
  "10.4": [
    [
      1280,
      191
    ],
    [
      35,
      194
    ],
    [
      0,
      205
    ],
    [
      0,
      566
    ],
    [
      1280,
      609
    ],
    [
      1280,
      191
    ]
  ],
  "10.5": [
    [
      1280,
      239
    ],
    [
      25,
      246
    ],
    [
      0,
      252
    ],
    [
      0,
      552
    ],
    [
      1280,
      587
    ],
    [
      1280,
      239
    ]
  ],
  "10.600000000000001": [
    [
      1280,
      188
    ],
    [
      0,
      197
    ],
    [
      0,
      552
    ],
    [
      1280,
      583
    ],
    [
      1280,
      188
    ]
  ],
  "10.700000000000001": [
    [
      1280,
      179
    ],
    [
      0,
      182
    ],
    [
      0,
      566
    ],
    [
      1280,
      600
    ],
    [
      1280,
      179
    ]
  ],
  "10.8": [
    [
      1280,
      189
    ],
    [
      0,
      117
    ],
    [
      0,
      546
    ],
    [
      1280,
      568
    ],
    [
      1280,
      189
    ]
  ],
  "10.9": [
    [
      1280,
      108
    ],
    [
      0,
      198
    ],
    [
      0,
      573
    ],
    [
      1280,
      588
    ],
    [
      1280,
      108
    ]
  ],
  "11.0": [
    [
      1280,
      173
    ],
    [
      0,
      193
    ],
    [
      0,
      566
    ],
    [
      1280,
      591
    ],
    [
      1280,
      173
    ]
  ],
  "11.100000000000001": [
    [
      1280,
      213
    ],
    [
      0,
      233
    ],
    [
      0,
      597
    ],
    [
      1280,
      620
    ],
    [
      1280,
      213
    ]
  ],
  "11.200000000000001": [
    [
      1280,
      206
    ],
    [
      0,
      222
    ],
    [
      0,
      582
    ],
    [
      1280,
      606
    ],
    [
      1280,
      206
    ]
  ],
  "11.3": [
    [
      1280,
      139
    ],
    [
      0,
      180
    ],
    [
      0,
      569
    ],
    [
      1280,
      603
    ],
    [
      1280,
      139
    ]
  ],
  "11.4": [
    [
      1280,
      169
    ],
    [
      0,
      157
    ],
    [
      0,
      586
    ],
    [
      1280,
      590
    ],
    [
      1280,
      169
    ]
  ],
  "11.5": [
    [
      1280,
      149
    ],
    [
      0,
      129
    ],
    [
      0,
      576
    ],
    [
      1280,
      567
    ],
    [
      1280,
      149
    ]
  ],
  "11.600000000000001": [
    [
      1280,
      182
    ],
    [
      0,
      230
    ],
    [
      0,
      589
    ],
    [
      1280,
      619
    ],
    [
      1280,
      182
    ]
  ],
  "11.700000000000001": [
    [
      1280,
      108
    ],
    [
      0,
      142
    ],
    [
      0,
      597
    ],
    [
      1280,
      621
    ],
    [
      1280,
      108
    ]
  ],
  "11.8": [
    [
      1280,
      198
    ],
    [
      0,
      200
    ],
    [
      0,
      593
    ],
    [
      1280,
      605
    ],
    [
      1280,
      198
    ]
  ],
  "11.9": [
    [
      1280,
      168
    ],
    [
      0,
      131
    ],
    [
      0,
      607
    ],
    [
      1280,
      594
    ],
    [
      1280,
      168
    ]
  ],
  "12.0": [
    [
      1280,
      192
    ],
    [
      0,
      191
    ],
    [
      0,
      603
    ],
    [
      1280,
      631
    ],
    [
      1280,
      192
    ]
  ],
  "12.100000000000001": [
    [
      1280,
      134
    ],
    [
      0,
      132
    ],
    [
      0,
      580
    ],
    [
      1280,
      586
    ],
    [
      1280,
      134
    ]
  ],
  "12.200000000000001": [
    [
      1280,
      147
    ],
    [
      0,
      157
    ],
    [
      0,
      616
    ],
    [
      1280,
      635
    ],
    [
      1280,
      147
    ]
  ],
  "12.3": [
    [
      1280,
      200
    ],
    [
      0,
      172
    ],
    [
      0,
      628
    ],
    [
      1280,
      606
    ],
    [
      1280,
      200
    ]
  ],
  "12.4": [
    [
      1280,
      176
    ],
    [
      0,
      141
    ],
    [
      0,
      588
    ],
    [
      1280,
      607
    ],
    [
      1280,
      176
    ]
  ],
  "12.5": [
    [
      1280,
      199
    ],
    [
      0,
      261
    ],
    [
      0,
      600
    ],
    [
      1280,
      668
    ],
    [
      1280,
      199
    ]
  ],
  "12.600000000000001": [
    [
      1280,
      162
    ],
    [
      0,
      160
    ],
    [
      0,
      580
    ],
    [
      1280,
      606
    ],
    [
      1280,
      162
    ]
  ],
  "12.700000000000001": [
    [
      1280,
      180
    ],
    [
      0,
      142
    ],
    [
      0,
      608
    ],
    [
      1280,
      627
    ],
    [
      1280,
      180
    ]
  ],
  "12.8": [
    [
      1280,
      155
    ],
    [
      0,
      149
    ],
    [
      0,
      597
    ],
    [
      1280,
      611
    ],
    [
      1280,
      155
    ]
  ],
  "12.9": [
    [
      1280,
      220
    ],
    [
      0,
      226
    ],
    [
      0,
      584
    ],
    [
      1280,
      611
    ],
    [
      1280,
      220
    ]
  ],
  "13.0": [
    [
      1280,
      150
    ],
    [
      0,
      158
    ],
    [
      0,
      603
    ],
    [
      1280,
      629
    ],
    [
      1280,
      150
    ]
  ],
  "13.100000000000001": [
    [
      1280,
      155
    ],
    [
      0,
      165
    ],
    [
      0,
      594
    ],
    [
      1280,
      624
    ],
    [
      1280,
      155
    ]
  ],
  "13.200000000000001": [
    [
      1280,
      184
    ],
    [
      0,
      157
    ],
    [
      0,
      605
    ],
    [
      1280,
      635
    ],
    [
      1280,
      184
    ]
  ],
  "13.3": [
    [
      1280,
      149
    ],
    [
      0,
      182
    ],
    [
      0,
      616
    ],
    [
      1280,
      642
    ],
    [
      1280,
      149
    ]
  ],
  "13.4": [
    [
      1280,
      153
    ],
    [
      0,
      147
    ],
    [
      0,
      593
    ],
    [
      1280,
      627
    ],
    [
      1280,
      153
    ]
  ],
  "13.5": [
    [
      1280,
      188
    ],
    [
      0,
      162
    ],
    [
      0,
      607
    ],
    [
      1280,
      631
    ],
    [
      1280,
      188
    ]
  ],
  "13.600000000000001": [
    [
      1280,
      144
    ],
    [
      0,
      127
    ],
    [
      0,
      603
    ],
    [
      1280,
      629
    ],
    [
      1280,
      144
    ]
  ],
  "13.700000000000001": [
    [
      1280,
      116
    ],
    [
      0,
      119
    ],
    [
      0,
      605
    ],
    [
      1280,
      611
    ],
    [
      1280,
      116
    ]
  ],
  "13.8": [
    [
      1280,
      144
    ],
    [
      0,
      139
    ],
    [
      0,
      619
    ],
    [
      1280,
      638
    ],
    [
      1280,
      144
    ]
  ],
  "13.9": [
    [
      1280,
      127
    ],
    [
      0,
      121
    ],
    [
      0,
      605
    ],
    [
      1280,
      619
    ],
    [
      1280,
      127
    ]
  ],
  "14.0": [
    [
      1280,
      193
    ],
    [
      0,
      178
    ],
    [
      0,
      642
    ],
    [
      1280,
      636
    ],
    [
      1280,
      193
    ]
  ],
  "14.100000000000001": [
    [
      1280,
      174
    ],
    [
      0,
      183
    ],
    [
      0,
      622
    ],
    [
      1280,
      644
    ],
    [
      1280,
      174
    ]
  ],
  "14.200000000000001": [
    [
      1280,
      116
    ],
    [
      0,
      107
    ],
    [
      0,
      625
    ],
    [
      1280,
      610
    ],
    [
      1280,
      116
    ]
  ],
  "14.3": [
    [
      1280,
      130
    ],
    [
      0,
      57
    ],
    [
      0,
      633
    ],
    [
      1280,
      641
    ],
    [
      1280,
      130
    ]
  ],
  "14.4": [
    [
      1280,
      131
    ],
    [
      0,
      99
    ],
    [
      0,
      633
    ],
    [
      1280,
      644
    ],
    [
      1280,
      131
    ]
  ],
  "14.5": [
    [
      1280,
      152
    ],
    [
      0,
      127
    ],
    [
      0,
      638
    ],
    [
      1280,
      647
    ],
    [
      1280,
      152
    ]
  ],
  "14.600000000000001": [
    [
      1280,
      174
    ],
    [
      0,
      126
    ],
    [
      0,
      649
    ],
    [
      1280,
      644
    ],
    [
      1280,
      174
    ]
  ],
  "14.700000000000001": [
    [
      1280,
      151
    ],
    [
      0,
      124
    ],
    [
      0,
      647
    ],
    [
      1280,
      658
    ],
    [
      1280,
      151
    ]
  ],
  "14.8": [
    [
      1280,
      176
    ],
    [
      0,
      131
    ],
    [
      0,
      649
    ],
    [
      1280,
      654
    ],
    [
      1280,
      176
    ]
  ],
  "14.9": [
    [
      1280,
      143
    ],
    [
      0,
      131
    ],
    [
      0,
      656
    ],
    [
      1280,
      647
    ],
    [
      1280,
      143
    ]
  ],
  "15.0": [
    [
      1280,
      192
    ],
    [
      0,
      122
    ],
    [
      0,
      679
    ],
    [
      1280,
      657
    ],
    [
      1280,
      192
    ]
  ],
  "15.100000000000001": [
    [
      1280,
      134
    ],
    [
      0,
      123
    ],
    [
      0,
      667
    ],
    [
      1280,
      671
    ],
    [
      1280,
      134
    ]
  ],
  "15.200000000000001": [
    [
      1280,
      153
    ],
    [
      0,
      101
    ],
    [
      0,
      682
    ],
    [
      1280,
      662
    ],
    [
      1280,
      153
    ]
  ],
  "15.3": [
    [
      1280,
      143
    ],
    [
      0,
      145
    ],
    [
      0,
      688
    ],
    [
      1280,
      680
    ],
    [
      1280,
      143
    ]
  ],
  "15.4": [
    [
      1280,
      169
    ],
    [
      0,
      147
    ],
    [
      0,
      689
    ],
    [
      1280,
      672
    ],
    [
      1280,
      169
    ]
  ],
  "15.5": [
    [
      1280,
      140
    ],
    [
      0,
      126
    ],
    [
      0,
      687
    ],
    [
      1280,
      663
    ],
    [
      1280,
      140
    ]
  ],
  "15.600000000000001": [
    [
      1280,
      162
    ],
    [
      0,
      107
    ],
    [
      0,
      702
    ],
    [
      1280,
      672
    ],
    [
      1280,
      162
    ]
  ],
  "15.700000000000001": [
    [
      1280,
      148
    ],
    [
      0,
      164
    ],
    [
      0,
      680
    ],
    [
      1280,
      695
    ],
    [
      1280,
      148
    ]
  ],
  "15.8": [
    [
      1280,
      151
    ],
    [
      0,
      135
    ],
    [
      0,
      704
    ],
    [
      1280,
      686
    ],
    [
      1280,
      151
    ]
  ],
  "15.9": [
    [
      1280,
      146
    ],
    [
      0,
      148
    ],
    [
      0,
      702
    ],
    [
      1280,
      695
    ],
    [
      1280,
      146
    ]
  ],
  "16.0": [
    [
      1280,
      148
    ],
    [
      0,
      159
    ],
    [
      0,
      702
    ],
    [
      1280,
      703
    ],
    [
      1280,
      148
    ]
  ],
  "16.1": [
    [
      1280,
      163
    ],
    [
      0,
      161
    ],
    [
      0,
      704
    ],
    [
      1280,
      697
    ],
    [
      1280,
      163
    ]
  ],
  "16.2": [
    [
      1280,
      167
    ],
    [
      0,
      138
    ],
    [
      0,
      720
    ],
    [
      381,
      720
    ],
    [
      1280,
      699
    ],
    [
      1280,
      167
    ]
  ],
  "16.3": [
    [
      1280,
      160
    ],
    [
      0,
      143
    ],
    [
      0,
      719
    ],
    [
      1280,
      716
    ],
    [
      1280,
      160
    ]
  ],
  "16.400000000000002": [
    [
      1280,
      163
    ],
    [
      0,
      152
    ],
    [
      0,
      720
    ],
    [
      184,
      720
    ],
    [
      1280,
      707
    ],
    [
      1280,
      163
    ]
  ],
  "16.5": [
    [
      1280,
      720
    ],
    [
      1280,
      187
    ],
    [
      0,
      217
    ],
    [
      0,
      710
    ],
    [
      539,
      720
    ],
    [
      1280,
      720
    ]
  ],
  "16.6": [
    [
      1280,
      163
    ],
    [
      0,
      129
    ],
    [
      0,
      720
    ],
    [
      555,
      720
    ],
    [
      1280,
      702
    ],
    [
      1280,
      163
    ]
  ],
  "16.7": [
    [
      1280,
      151
    ],
    [
      0,
      156
    ],
    [
      0,
      720
    ],
    [
      57,
      720
    ],
    [
      1280,
      717
    ],
    [
      1280,
      151
    ]
  ],
  "16.8": [
    [
      1280,
      196
    ],
    [
      0,
      159
    ],
    [
      0,
      720
    ],
    [
      793,
      720
    ],
    [
      1280,
      705
    ],
    [
      1280,
      196
    ]
  ],
  "16.900000000000002": [
    [
      0,
      720
    ],
    [
      1280,
      720
    ],
    [
      1280,
      129
    ],
    [
      0,
      130
    ],
    [
      0,
      720
    ]
  ],
  "17.0": [
    [
      0,
      720
    ],
    [
      1280,
      720
    ],
    [
      1280,
      136
    ],
    [
      0,
      157
    ],
    [
      0,
      720
    ]
  ],
  "17.1": [
    [
      0,
      720
    ],
    [
      1280,
      720
    ],
    [
      1280,
      107
    ],
    [
      0,
      176
    ],
    [
      0,
      720
    ]
  ],
  "17.2": [
    [
      0,
      720
    ],
    [
      1280,
      720
    ],
    [
      1280,
      129
    ],
    [
      0,
      147
    ],
    [
      0,
      720
    ]
  ],
  "17.3": [
    [
      0,
      720
    ],
    [
      1280,
      720
    ],
    [
      1280,
      106
    ],
    [
      0,
      143
    ],
    [
      0,
      720
    ]
  ],
  "17.400000000000002": [
    [
      1280,
      129
    ],
    [
      0,
      171
    ],
    [
      0,
      720
    ],
    [
      614,
      720
    ],
    [
      1280,
      709
    ],
    [
      1280,
      129
    ]
  ],
  "17.5": [
    [
      1280,
      127
    ],
    [
      0,
      184
    ],
    [
      0,
      720
    ],
    [
      424,
      720
    ],
    [
      1280,
      709
    ],
    [
      1280,
      127
    ]
  ],
  "17.6": [
    [
      0,
      720
    ],
    [
      1280,
      720
    ],
    [
      1280,
      140
    ],
    [
      0,
      168
    ],
    [
      0,
      720
    ]
  ],
  "17.7": [
    [
      1280,
      181
    ],
    [
      0,
      191
    ],
    [
      0,
      720
    ],
    [
      1008,
      720
    ],
    [
      1280,
      713
    ],
    [
      1280,
      181
    ]
  ],
  "17.8": [
    [
      0,
      720
    ],
    [
      1280,
      720
    ],
    [
      1280,
      123
    ],
    [
      0,
      157
    ],
    [
      0,
      720
    ]
  ],
  "17.900000000000002": [
    [
      0,
      720
    ],
    [
      1280,
      720
    ],
    [
      1280,
      157
    ],
    [
      0,
      224
    ],
    [
      0,
      720
    ]
  ],
  "18.0": [
    [
      1280,
      107
    ],
    [
      0,
      149
    ],
    [
      0,
      720
    ],
    [
      852,
      720
    ],
    [
      1280,
      707
    ],
    [
      1280,
      107
    ]
  ],
  "18.1": [
    [
      0,
      720
    ],
    [
      1280,
      720
    ],
    [
      1280,
      121
    ],
    [
      0,
      140
    ],
    [
      0,
      720
    ]
  ],
  "18.2": [
    [
      0,
      720
    ],
    [
      1280,
      720
    ],
    [
      1280,
      126
    ],
    [
      0,
      169
    ],
    [
      0,
      720
    ]
  ],
  "18.3": [
    [
      1280,
      104
    ],
    [
      0,
      145
    ],
    [
      0,
      720
    ],
    [
      1082,
      720
    ],
    [
      1280,
      713
    ],
    [
      1280,
      104
    ]
  ],
  "18.400000000000002": [
    [
      1280,
      129
    ],
    [
      0,
      128
    ],
    [
      0,
      720
    ],
    [
      1033,
      720
    ],
    [
      1280,
      710
    ],
    [
      1280,
      129
    ]
  ],
  "18.5": [
    [
      0,
      720
    ],
    [
      1280,
      720
    ],
    [
      1280,
      160
    ],
    [
      0,
      215
    ],
    [
      0,
      720
    ]
  ],
  "18.6": [
    [
      1280,
      114
    ],
    [
      0,
      115
    ],
    [
      0,
      720
    ],
    [
      1262,
      720
    ],
    [
      1280,
      719
    ],
    [
      1280,
      114
    ]
  ],
  "18.7": [
    [
      0,
      720
    ],
    [
      1280,
      720
    ],
    [
      1280,
      110
    ],
    [
      0,
      191
    ],
    [
      0,
      720
    ]
  ],
  "18.8": [
    [
      0,
      720
    ],
    [
      1280,
      720
    ],
    [
      1280,
      134
    ],
    [
      0,
      179
    ],
    [
      0,
      720
    ]
  ],
  "18.900000000000002": [
    [
      0,
      720
    ],
    [
      1280,
      720
    ],
    [
      1280,
      110
    ],
    [
      0,
      147
    ],
    [
      0,
      720
    ]
  ],
  "19.0": [
    [
      0,
      720
    ],
    [
      1280,
      720
    ],
    [
      1280,
      117
    ],
    [
      0,
      133
    ],
    [
      0,
      720
    ]
  ],
  "19.1": [
    [
      0,
      720
    ],
    [
      1280,
      720
    ],
    [
      1280,
      119
    ],
    [
      0,
      167
    ],
    [
      0,
      720
    ]
  ],
  "19.200000000000003": [
    [
      0,
      720
    ],
    [
      1280,
      720
    ],
    [
      1280,
      176
    ],
    [
      0,
      196
    ],
    [
      0,
      720
    ]
  ],
  "19.3": [
    [
      1280,
      166
    ],
    [
      0,
      150
    ],
    [
      0,
      720
    ],
    [
      1279,
      720
    ],
    [
      1280,
      719
    ],
    [
      1280,
      166
    ]
  ],
  "19.400000000000002": [
    [
      0,
      720
    ],
    [
      1280,
      720
    ],
    [
      1280,
      207
    ],
    [
      0,
      260
    ],
    [
      0,
      720
    ]
  ],
  "19.5": [
    [
      0,
      720
    ],
    [
      1280,
      720
    ],
    [
      1280,
      112
    ],
    [
      0,
      156
    ],
    [
      0,
      720
    ]
  ],
  "19.6": [
    [
      0,
      720
    ],
    [
      1280,
      720
    ],
    [
      1280,
      165
    ],
    [
      0,
      185
    ],
    [
      0,
      720
    ]
  ],
  "19.700000000000003": [
    [
      0,
      720
    ],
    [
      1280,
      720
    ],
    [
      1280,
      135
    ],
    [
      0,
      158
    ],
    [
      0,
      720
    ]
  ],
  "19.8": [
    [
      0,
      720
    ],
    [
      1280,
      720
    ],
    [
      1280,
      63
    ],
    [
      0,
      79
    ],
    [
      0,
      720
    ]
  ],
  "19.900000000000002": [
    [
      0,
      720
    ],
    [
      1280,
      720
    ],
    [
      1280,
      94
    ],
    [
      0,
      141
    ],
    [
      0,
      720
    ]
  ],
  "20.0": [
    [
      0,
      720
    ],
    [
      1280,
      720
    ],
    [
      1280,
      104
    ],
    [
      0,
      127
    ],
    [
      0,
      720
    ]
  ],
  "20.1": [
    [
      0,
      720
    ],
    [
      1280,
      720
    ],
    [
      1280,
      103
    ],
    [
      0,
      135
    ],
    [
      0,
      720
    ]
  ],
  "20.200000000000003": [
    [
      0,
      720
    ],
    [
      1280,
      720
    ],
    [
      1280,
      137
    ],
    [
      0,
      148
    ],
    [
      0,
      720
    ]
  ],
  "20.3": [
    [
      0,
      720
    ],
    [
      1280,
      720
    ],
    [
      1280,
      108
    ],
    [
      0,
      138
    ],
    [
      0,
      720
    ]
  ],
  "20.400000000000002": [
    [
      0,
      720
    ],
    [
      1280,
      720
    ],
    [
      1280,
      166
    ],
    [
      0,
      205
    ],
    [
      0,
      720
    ]
  ],
  "20.5": [
    [
      1280,
      136
    ],
    [
      0,
      182
    ],
    [
      0,
      720
    ],
    [
      1234,
      720
    ],
    [
      1280,
      716
    ],
    [
      1280,
      136
    ]
  ],
  "20.6": [
    [
      1280,
      171
    ],
    [
      0,
      143
    ],
    [
      0,
      720
    ],
    [
      1132,
      720
    ],
    [
      1280,
      706
    ],
    [
      1280,
      171
    ]
  ],
  "20.700000000000003": [
    [
      1280,
      142
    ],
    [
      0,
      130
    ],
    [
      0,
      720
    ],
    [
      979,
      720
    ],
    [
      1280,
      693
    ],
    [
      1280,
      142
    ]
  ],
  "20.8": [
    [
      1280,
      144
    ],
    [
      0,
      155
    ],
    [
      0,
      720
    ],
    [
      1083,
      720
    ],
    [
      1280,
      703
    ],
    [
      1280,
      144
    ]
  ],
  "20.900000000000002": [
    [
      0,
      720
    ],
    [
      1280,
      720
    ],
    [
      1280,
      112
    ],
    [
      0,
      159
    ],
    [
      0,
      720
    ]
  ],
  "21.0": [
    [
      1280,
      181
    ],
    [
      1257,
      173
    ],
    [
      0,
      178
    ],
    [
      0,
      720
    ],
    [
      806,
      720
    ],
    [
      1280,
      684
    ],
    [
      1280,
      181
    ]
  ],
  "21.1": [
    [
      1280,
      149
    ],
    [
      0,
      150
    ],
    [
      0,
      720
    ],
    [
      850,
      720
    ],
    [
      1280,
      688
    ],
    [
      1280,
      149
    ]
  ],
  "21.200000000000003": [
    [
      1280,
      113
    ],
    [
      1198,
      86
    ],
    [
      0,
      178
    ],
    [
      0,
      720
    ],
    [
      899,
      720
    ],
    [
      1280,
      695
    ],
    [
      1280,
      113
    ]
  ],
  "21.3": [
    [
      1280,
      105
    ],
    [
      1231,
      89
    ],
    [
      0,
      186
    ],
    [
      0,
      720
    ],
    [
      689,
      720
    ],
    [
      1280,
      684
    ],
    [
      1280,
      105
    ]
  ],
  "21.400000000000002": [
    [
      1280,
      166
    ],
    [
      1155,
      120
    ],
    [
      0,
      172
    ],
    [
      0,
      720
    ],
    [
      831,
      720
    ],
    [
      1280,
      683
    ],
    [
      1280,
      166
    ]
  ],
  "21.5": [
    [
      1280,
      143
    ],
    [
      1124,
      86
    ],
    [
      0,
      141
    ],
    [
      0,
      720
    ],
    [
      742,
      720
    ],
    [
      1280,
      677
    ],
    [
      1280,
      143
    ]
  ],
  "21.6": [
    [
      1280,
      198
    ],
    [
      1047,
      101
    ],
    [
      0,
      121
    ],
    [
      0,
      720
    ],
    [
      875,
      720
    ],
    [
      1280,
      678
    ],
    [
      1280,
      198
    ]
  ],
  "21.700000000000003": [
    [
      1280,
      173
    ],
    [
      1054,
      93
    ],
    [
      0,
      159
    ],
    [
      0,
      720
    ],
    [
      728,
      720
    ],
    [
      1280,
      684
    ],
    [
      1280,
      173
    ]
  ],
  "21.8": [
    [
      1280,
      225
    ],
    [
      948,
      99
    ],
    [
      0,
      125
    ],
    [
      0,
      720
    ],
    [
      897,
      720
    ],
    [
      1280,
      681
    ],
    [
      1280,
      225
    ]
  ],
  "21.900000000000002": [
    [
      1280,
      239
    ],
    [
      922,
      97
    ],
    [
      0,
      131
    ],
    [
      0,
      720
    ],
    [
      819,
      720
    ],
    [
      1280,
      680
    ],
    [
      1280,
      239
    ]
  ],
  "22.0": [
    [
      1280,
      242
    ],
    [
      899,
      83
    ],
    [
      0,
      88
    ],
    [
      0,
      720
    ],
    [
      848,
      720
    ],
    [
      1280,
      667
    ],
    [
      1280,
      242
    ]
  ],
  "22.1": [
    [
      1280,
      292
    ],
    [
      959,
      187
    ],
    [
      0,
      196
    ],
    [
      0,
      720
    ],
    [
      780,
      720
    ],
    [
      1280,
      673
    ],
    [
      1280,
      292
    ]
  ],
  "22.200000000000003": [
    [
      1280,
      252
    ],
    [
      844,
      107
    ],
    [
      0,
      167
    ],
    [
      0,
      720
    ],
    [
      794,
      720
    ],
    [
      1280,
      678
    ],
    [
      1280,
      252
    ]
  ],
  "22.3": [
    [
      1280,
      257
    ],
    [
      866,
      104
    ],
    [
      0,
      150
    ],
    [
      0,
      720
    ],
    [
      755,
      720
    ],
    [
      1280,
      674
    ],
    [
      1280,
      257
    ]
  ],
  "22.400000000000002": [
    [
      1280,
      267
    ],
    [
      886,
      105
    ],
    [
      0,
      131
    ],
    [
      0,
      720
    ],
    [
      860,
      720
    ],
    [
      1280,
      668
    ],
    [
      1280,
      267
    ]
  ],
  "22.5": [
    [
      1280,
      241
    ],
    [
      766,
      106
    ],
    [
      0,
      190
    ],
    [
      0,
      720
    ],
    [
      882,
      720
    ],
    [
      1280,
      692
    ],
    [
      1280,
      241
    ]
  ],
  "22.6": [
    [
      1280,
      294
    ],
    [
      751,
      98
    ],
    [
      0,
      130
    ],
    [
      0,
      720
    ],
    [
      1003,
      720
    ],
    [
      1280,
      691
    ],
    [
      1280,
      294
    ]
  ],
  "22.700000000000003": [
    [
      1280,
      271
    ],
    [
      737,
      106
    ],
    [
      0,
      169
    ],
    [
      0,
      720
    ],
    [
      706,
      720
    ],
    [
      1280,
      668
    ],
    [
      1280,
      271
    ]
  ],
  "22.8": [
    [
      1280,
      303
    ],
    [
      837,
      164
    ],
    [
      0,
      192
    ],
    [
      0,
      720
    ],
    [
      611,
      720
    ],
    [
      1280,
      655
    ],
    [
      1280,
      303
    ]
  ],
  "22.900000000000002": [
    [
      0,
      720
    ],
    [
      1280,
      720
    ],
    [
      1280,
      276
    ],
    [
      670,
      71
    ],
    [
      0,
      114
    ],
    [
      0,
      720
    ]
  ],
  "23.0": [
    [
      1280,
      299
    ],
    [
      670,
      85
    ],
    [
      0,
      127
    ],
    [
      0,
      720
    ],
    [
      967,
      720
    ],
    [
      1280,
      678
    ],
    [
      1280,
      299
    ]
  ],
  "23.1": [
    [
      1280,
      312
    ],
    [
      666,
      113
    ],
    [
      0,
      165
    ],
    [
      0,
      720
    ],
    [
      873,
      720
    ],
    [
      1280,
      679
    ],
    [
      1280,
      312
    ]
  ],
  "23.200000000000003": [
    [
      1280,
      318
    ],
    [
      641,
      84
    ],
    [
      0,
      120
    ],
    [
      0,
      720
    ],
    [
      1060,
      720
    ],
    [
      1280,
      689
    ],
    [
      1280,
      318
    ]
  ],
  "23.3": [
    [
      1280,
      319
    ],
    [
      654,
      97
    ],
    [
      0,
      138
    ],
    [
      0,
      720
    ],
    [
      991,
      720
    ],
    [
      1280,
      682
    ],
    [
      1280,
      319
    ]
  ],
  "23.400000000000002": [
    [
      1280,
      314
    ],
    [
      637,
      76
    ],
    [
      0,
      121
    ],
    [
      0,
      720
    ],
    [
      962,
      720
    ],
    [
      1280,
      679
    ],
    [
      1280,
      314
    ]
  ],
  "23.5": [
    [
      1280,
      306
    ],
    [
      660,
      83
    ],
    [
      0,
      123
    ],
    [
      0,
      720
    ],
    [
      738,
      720
    ],
    [
      1280,
      650
    ],
    [
      1280,
      306
    ]
  ],
  "23.6": [
    [
      1280,
      296
    ],
    [
      659,
      78
    ],
    [
      0,
      127
    ],
    [
      0,
      720
    ],
    [
      908,
      720
    ],
    [
      1280,
      677
    ],
    [
      1280,
      296
    ]
  ],
  "23.700000000000003": [
    [
      1280,
      336
    ],
    [
      777,
      214
    ],
    [
      0,
      246
    ],
    [
      0,
      720
    ],
    [
      590,
      720
    ],
    [
      1280,
      657
    ],
    [
      1280,
      336
    ]
  ],
  "23.8": [
    [
      1280,
      280
    ],
    [
      733,
      105
    ],
    [
      0,
      169
    ],
    [
      0,
      720
    ],
    [
      914,
      720
    ],
    [
      1280,
      680
    ],
    [
      1280,
      280
    ]
  ],
  "23.900000000000002": [
    [
      1280,
      280
    ],
    [
      775,
      104
    ],
    [
      0,
      136
    ],
    [
      0,
      720
    ],
    [
      818,
      720
    ],
    [
      1280,
      657
    ],
    [
      1280,
      280
    ]
  ],
  "24.0": [
    [
      1280,
      308
    ],
    [
      756,
      93
    ],
    [
      0,
      101
    ],
    [
      0,
      720
    ],
    [
      794,
      720
    ],
    [
      1280,
      659
    ],
    [
      1280,
      308
    ]
  ],
  "24.1": [
    [
      1280,
      268
    ],
    [
      799,
      105
    ],
    [
      0,
      147
    ],
    [
      0,
      720
    ],
    [
      745,
      720
    ],
    [
      1280,
      657
    ],
    [
      1280,
      268
    ]
  ],
  "24.200000000000003": [
    [
      1280,
      269
    ],
    [
      752,
      74
    ],
    [
      0,
      122
    ],
    [
      0,
      720
    ],
    [
      1086,
      720
    ],
    [
      1280,
      693
    ],
    [
      1280,
      269
    ]
  ],
  "24.3": [
    [
      1280,
      285
    ],
    [
      778,
      104
    ],
    [
      0,
      136
    ],
    [
      0,
      720
    ],
    [
      724,
      720
    ],
    [
      1280,
      652
    ],
    [
      1280,
      285
    ]
  ],
  "24.400000000000002": [
    [
      1280,
      278
    ],
    [
      748,
      94
    ],
    [
      0,
      143
    ],
    [
      0,
      720
    ],
    [
      775,
      720
    ],
    [
      1280,
      659
    ],
    [
      1280,
      278
    ]
  ],
  "24.5": [
    [
      1280,
      276
    ],
    [
      808,
      122
    ],
    [
      0,
      154
    ],
    [
      0,
      720
    ],
    [
      648,
      720
    ],
    [
      1280,
      634
    ],
    [
      1280,
      276
    ]
  ],
  "24.6": [
    [
      1280,
      292
    ],
    [
      763,
      108
    ],
    [
      0,
      156
    ],
    [
      0,
      720
    ],
    [
      692,
      720
    ],
    [
      1280,
      658
    ],
    [
      1280,
      292
    ]
  ],
  "24.700000000000003": [
    [
      1280,
      293
    ],
    [
      756,
      110
    ],
    [
      0,
      148
    ],
    [
      0,
      720
    ],
    [
      712,
      720
    ],
    [
      1280,
      645
    ],
    [
      1280,
      293
    ]
  ],
  "24.8": [
    [
      1280,
      291
    ],
    [
      734,
      114
    ],
    [
      0,
      165
    ],
    [
      0,
      720
    ],
    [
      711,
      720
    ],
    [
      1280,
      647
    ],
    [
      1280,
      291
    ]
  ],
  "24.900000000000002": [
    [
      1280,
      313
    ],
    [
      723,
      117
    ],
    [
      0,
      157
    ],
    [
      0,
      720
    ],
    [
      731,
      720
    ],
    [
      1280,
      651
    ],
    [
      1280,
      313
    ]
  ],
  "25.0": [
    [
      1280,
      330
    ],
    [
      754,
      153
    ],
    [
      0,
      198
    ],
    [
      0,
      720
    ],
    [
      609,
      720
    ],
    [
      1280,
      649
    ],
    [
      1280,
      330
    ]
  ],
  "25.1": [
    [
      1280,
      349
    ],
    [
      757,
      202
    ],
    [
      0,
      240
    ],
    [
      0,
      720
    ],
    [
      616,
      720
    ],
    [
      1280,
      649
    ],
    [
      1280,
      349
    ]
  ],
  "25.200000000000003": [
    [
      1280,
      323
    ],
    [
      741,
      167
    ],
    [
      0,
      241
    ],
    [
      0,
      720
    ],
    [
      608,
      720
    ],
    [
      1280,
      668
    ],
    [
      1280,
      323
    ]
  ],
  "25.3": [
    [
      1280,
      314
    ],
    [
      743,
      123
    ],
    [
      0,
      193
    ],
    [
      0,
      720
    ],
    [
      648,
      720
    ],
    [
      1280,
      665
    ],
    [
      1280,
      314
    ]
  ],
  "25.400000000000002": [
    [
      1280,
      316
    ],
    [
      685,
      113
    ],
    [
      0,
      166
    ],
    [
      0,
      720
    ],
    [
      733,
      720
    ],
    [
      1280,
      642
    ],
    [
      1280,
      316
    ]
  ],
  "25.5": [
    [
      1280,
      337
    ],
    [
      674,
      129
    ],
    [
      0,
      173
    ],
    [
      0,
      720
    ],
    [
      754,
      720
    ],
    [
      1280,
      641
    ],
    [
      1280,
      337
    ]
  ],
  "25.6": [
    [
      1280,
      325
    ],
    [
      664,
      114
    ],
    [
      0,
      170
    ],
    [
      0,
      720
    ],
    [
      706,
      720
    ],
    [
      1280,
      645
    ],
    [
      1280,
      325
    ]
  ],
  "25.700000000000003": [
    [
      1280,
      331
    ],
    [
      671,
      119
    ],
    [
      0,
      160
    ],
    [
      0,
      720
    ],
    [
      864,
      720
    ],
    [
      1280,
      655
    ],
    [
      1280,
      331
    ]
  ],
  "25.8": [
    [
      1280,
      364
    ],
    [
      675,
      142
    ],
    [
      0,
      179
    ],
    [
      0,
      720
    ],
    [
      910,
      720
    ],
    [
      1280,
      668
    ],
    [
      1280,
      364
    ]
  ],
  "25.900000000000002": [
    [
      1280,
      333
    ],
    [
      669,
      124
    ],
    [
      0,
      169
    ],
    [
      0,
      720
    ],
    [
      823,
      720
    ],
    [
      1280,
      656
    ],
    [
      1280,
      333
    ]
  ],
  "26.0": [
    [
      1280,
      357
    ],
    [
      628,
      122
    ],
    [
      0,
      176
    ],
    [
      0,
      720
    ],
    [
      978,
      720
    ],
    [
      1280,
      678
    ],
    [
      1280,
      357
    ]
  ],
  "26.1": [
    [
      1280,
      353
    ],
    [
      634,
      103
    ],
    [
      0,
      150
    ],
    [
      0,
      720
    ],
    [
      981,
      720
    ],
    [
      1280,
      675
    ],
    [
      1280,
      353
    ]
  ],
  "26.200000000000003": [
    [
      1280,
      361
    ],
    [
      624,
      127
    ],
    [
      0,
      176
    ],
    [
      0,
      720
    ],
    [
      961,
      720
    ],
    [
      1280,
      674
    ],
    [
      1280,
      361
    ]
  ],
  "26.3": [
    [
      1280,
      339
    ],
    [
      640,
      162
    ],
    [
      0,
      235
    ],
    [
      0,
      720
    ],
    [
      999,
      720
    ],
    [
      1280,
      690
    ],
    [
      1280,
      339
    ]
  ],
  "26.400000000000002": [
    [
      1280,
      359
    ],
    [
      611,
      127
    ],
    [
      0,
      176
    ],
    [
      0,
      720
    ],
    [
      940,
      720
    ],
    [
      1280,
      667
    ],
    [
      1280,
      359
    ]
  ],
  "26.5": [
    [
      1280,
      390
    ],
    [
      634,
      141
    ],
    [
      0,
      188
    ],
    [
      0,
      720
    ],
    [
      1072,
      720
    ],
    [
      1280,
      692
    ],
    [
      1280,
      390
    ]
  ],
  "26.6": [
    [
      1280,
      381
    ],
    [
      623,
      157
    ],
    [
      0,
      212
    ],
    [
      0,
      720
    ],
    [
      964,
      720
    ],
    [
      1280,
      680
    ],
    [
      1280,
      381
    ]
  ],
  "26.700000000000003": [
    [
      1280,
      384
    ],
    [
      603,
      134
    ],
    [
      0,
      185
    ],
    [
      0,
      720
    ],
    [
      1025,
      720
    ],
    [
      1280,
      686
    ],
    [
      1280,
      384
    ]
  ],
  "26.8": [
    [
      1280,
      374
    ],
    [
      578,
      142
    ],
    [
      0,
      203
    ],
    [
      0,
      720
    ],
    [
      1114,
      720
    ],
    [
      1280,
      700
    ],
    [
      1280,
      374
    ]
  ],
  "26.900000000000002": [
    [
      1280,
      366
    ],
    [
      595,
      131
    ],
    [
      0,
      186
    ],
    [
      0,
      720
    ],
    [
      1065,
      720
    ],
    [
      1280,
      690
    ],
    [
      1280,
      366
    ]
  ],
  "27.0": [
    [
      1280,
      391
    ],
    [
      575,
      132
    ],
    [
      0,
      183
    ],
    [
      0,
      720
    ],
    [
      1124,
      720
    ],
    [
      1280,
      697
    ],
    [
      1280,
      391
    ]
  ],
  "27.1": [
    [
      1280,
      389
    ],
    [
      608,
      160
    ],
    [
      0,
      203
    ],
    [
      0,
      720
    ],
    [
      1005,
      720
    ],
    [
      1280,
      680
    ],
    [
      1280,
      389
    ]
  ],
  "27.200000000000003": [
    [
      1280,
      395
    ],
    [
      614,
      170
    ],
    [
      0,
      207
    ],
    [
      0,
      720
    ],
    [
      955,
      720
    ],
    [
      1280,
      671
    ],
    [
      1280,
      395
    ]
  ],
  "27.3": [
    [
      1280,
      386
    ],
    [
      562,
      154
    ],
    [
      0,
      214
    ],
    [
      0,
      720
    ],
    [
      1177,
      720
    ],
    [
      1280,
      707
    ],
    [
      1280,
      386
    ]
  ],
  "27.400000000000002": [
    [
      1280,
      383
    ],
    [
      583,
      149
    ],
    [
      0,
      197
    ],
    [
      0,
      720
    ],
    [
      978,
      720
    ],
    [
      1280,
      674
    ],
    [
      1280,
      383
    ]
  ],
  "27.5": [
    [
      1280,
      396
    ],
    [
      552,
      156
    ],
    [
      0,
      226
    ],
    [
      0,
      720
    ],
    [
      1271,
      720
    ],
    [
      1280,
      719
    ],
    [
      1280,
      396
    ]
  ],
  "27.6": [
    [
      1280,
      392
    ],
    [
      550,
      145
    ],
    [
      0,
      206
    ],
    [
      0,
      720
    ],
    [
      1260,
      720
    ],
    [
      1280,
      717
    ],
    [
      1280,
      392
    ]
  ],
  "27.700000000000003": [
    [
      1280,
      381
    ],
    [
      562,
      129
    ],
    [
      0,
      182
    ],
    [
      0,
      720
    ],
    [
      1123,
      720
    ],
    [
      1280,
      699
    ],
    [
      1280,
      381
    ]
  ],
  "27.8": [
    [
      1280,
      406
    ],
    [
      613,
      256
    ],
    [
      0,
      309
    ],
    [
      0,
      720
    ],
    [
      935,
      720
    ],
    [
      1280,
      698
    ],
    [
      1280,
      406
    ]
  ],
  "27.900000000000002": [
    [
      1280,
      383
    ],
    [
      561,
      144
    ],
    [
      0,
      200
    ],
    [
      0,
      720
    ],
    [
      1130,
      720
    ],
    [
      1280,
      699
    ],
    [
      1280,
      383
    ]
  ],
  "28.0": [
    [
      1280,
      405
    ],
    [
      588,
      153
    ],
    [
      0,
      183
    ],
    [
      0,
      720
    ],
    [
      987,
      720
    ],
    [
      1280,
      673
    ],
    [
      1280,
      405
    ]
  ],
  "28.1": [
    [
      1280,
      387
    ],
    [
      577,
      144
    ],
    [
      0,
      199
    ],
    [
      0,
      720
    ],
    [
      1243,
      720
    ],
    [
      1280,
      715
    ],
    [
      1280,
      387
    ]
  ],
  "28.200000000000003": [
    [
      1280,
      397
    ],
    [
      571,
      149
    ],
    [
      0,
      205
    ],
    [
      0,
      720
    ],
    [
      1278,
      720
    ],
    [
      1280,
      719
    ],
    [
      1280,
      397
    ]
  ],
  "28.3": [
    [
      1280,
      358
    ],
    [
      601,
      136
    ],
    [
      0,
      192
    ],
    [
      0,
      720
    ],
    [
      1055,
      720
    ],
    [
      1280,
      689
    ],
    [
      1280,
      358
    ]
  ],
  "28.400000000000002": [
    [
      1280,
      362
    ],
    [
      619,
      151
    ],
    [
      0,
      208
    ],
    [
      0,
      720
    ],
    [
      1198,
      720
    ],
    [
      1280,
      708
    ],
    [
      1280,
      362
    ]
  ],
  "28.5": [
    [
      1280,
      358
    ],
    [
      663,
      133
    ],
    [
      0,
      175
    ],
    [
      0,
      720
    ],
    [
      1074,
      720
    ],
    [
      1280,
      690
    ],
    [
      1280,
      358
    ]
  ],
  "28.6": [
    [
      1280,
      0
    ],
    [
      0,
      0
    ],
    [
      0,
      148
    ],
    [
      689,
      136
    ],
    [
      1280,
      362
    ],
    [
      1280,
      0
    ]
  ],
  "28.700000000000003": [
    [
      1280,
      348
    ],
    [
      772,
      158
    ],
    [
      0,
      174
    ],
    [
      0,
      720
    ],
    [
      1276,
      720
    ],
    [
      1280,
      719
    ],
    [
      1280,
      348
    ]
  ],
  "28.8": [
    [
      0,
      720
    ],
    [
      1280,
      720
    ],
    [
      1280,
      328
    ],
    [
      802,
      144
    ],
    [
      0,
      183
    ],
    [
      0,
      720
    ]
  ],
  "28.900000000000002": [
    [
      0,
      720
    ],
    [
      1280,
      720
    ],
    [
      1280,
      301
    ],
    [
      817,
      146
    ],
    [
      0,
      198
    ],
    [
      0,
      720
    ]
  ],
  "29.0": [
    [
      1280,
      328
    ],
    [
      866,
      161
    ],
    [
      0,
      171
    ],
    [
      0,
      720
    ],
    [
      1258,
      720
    ],
    [
      1280,
      716
    ],
    [
      1280,
      328
    ]
  ],
  "29.1": [
    [
      0,
      720
    ],
    [
      1280,
      720
    ],
    [
      1280,
      311
    ],
    [
      897,
      137
    ],
    [
      0,
      143
    ],
    [
      0,
      720
    ]
  ],
  "29.200000000000003": [
    [
      0,
      720
    ],
    [
      1280,
      720
    ],
    [
      1280,
      283
    ],
    [
      930,
      145
    ],
    [
      0,
      178
    ],
    [
      0,
      720
    ]
  ],
  "29.3": [
    [
      0,
      720
    ],
    [
      1280,
      720
    ],
    [
      1280,
      260
    ],
    [
      955,
      145
    ],
    [
      0,
      180
    ],
    [
      0,
      720
    ]
  ],
  "29.400000000000002": [
    [
      0,
      720
    ],
    [
      1280,
      720
    ],
    [
      1280,
      228
    ],
    [
      968,
      124
    ],
    [
      0,
      174
    ],
    [
      0,
      720
    ]
  ],
  "29.5": [
    [
      0,
      720
    ],
    [
      1280,
      720
    ],
    [
      1280,
      268
    ],
    [
      1057,
      158
    ],
    [
      0,
      144
    ],
    [
      0,
      720
    ]
  ],
  "29.6": [
    [
      0,
      720
    ],
    [
      1280,
      720
    ],
    [
      1280,
      215
    ],
    [
      1104,
      143
    ],
    [
      0,
      186
    ],
    [
      0,
      720
    ]
  ],
  "29.700000000000003": [
    [
      0,
      720
    ],
    [
      1280,
      720
    ],
    [
      1280,
      166
    ],
    [
      1135,
      105
    ],
    [
      0,
      190
    ],
    [
      0,
      720
    ]
  ],
  "29.8": [
    [
      0,
      720
    ],
    [
      1280,
      720
    ],
    [
      1280,
      207
    ],
    [
      1124,
      146
    ],
    [
      0,
      176
    ],
    [
      0,
      720
    ]
  ],
  "29.900000000000002": [
    [
      0,
      720
    ],
    [
      1280,
      720
    ],
    [
      1280,
      264
    ],
    [
      1207,
      249
    ],
    [
      0,
      316
    ],
    [
      0,
      720
    ]
  ],
  "30.0": [
    [
      0,
      720
    ],
    [
      1280,
      720
    ],
    [
      1280,
      162
    ],
    [
      1170,
      123
    ],
    [
      0,
      222
    ],
    [
      0,
      720
    ]
  ],
  "30.1": [
    [
      0,
      720
    ],
    [
      1280,
      720
    ],
    [
      1280,
      194
    ],
    [
      1206,
      164
    ],
    [
      0,
      199
    ],
    [
      0,
      720
    ]
  ],
  "30.200000000000003": [
    [
      0,
      720
    ],
    [
      1280,
      720
    ],
    [
      1280,
      227
    ],
    [
      1179,
      194
    ],
    [
      0,
      228
    ],
    [
      0,
      720
    ]
  ],
  "30.3": [
    [
      0,
      720
    ],
    [
      1280,
      720
    ],
    [
      1280,
      328
    ],
    [
      1179,
      305
    ],
    [
      0,
      298
    ],
    [
      0,
      720
    ]
  ],
  "30.400000000000002": [
    [
      0,
      720
    ],
    [
      1280,
      720
    ],
    [
      1280,
      222
    ],
    [
      1223,
      200
    ],
    [
      0,
      207
    ],
    [
      0,
      720
    ]
  ],
  "30.5": [
    [
      0,
      720
    ],
    [
      1280,
      720
    ],
    [
      1280,
      289
    ],
    [
      1195,
      259
    ],
    [
      0,
      234
    ],
    [
      0,
      720
    ]
  ],
  "30.6": [
    [
      0,
      720
    ],
    [
      1280,
      720
    ],
    [
      1280,
      252
    ],
    [
      1209,
      233
    ],
    [
      0,
      256
    ],
    [
      0,
      720
    ]
  ],
  "30.700000000000003": [
    [
      0,
      720
    ],
    [
      1280,
      720
    ],
    [
      1280,
      201
    ],
    [
      1279,
      201
    ],
    [
      0,
      224
    ],
    [
      0,
      720
    ]
  ],
  "30.8": [
    [
      0,
      720
    ],
    [
      1280,
      720
    ],
    [
      1280,
      183
    ],
    [
      0,
      206
    ],
    [
      0,
      720
    ]
  ],
  "30.900000000000002": [
    [
      0,
      720
    ],
    [
      1280,
      720
    ],
    [
      1280,
      178
    ],
    [
      0,
      212
    ],
    [
      0,
      720
    ]
  ],
  "31.0": [
    [
      0,
      720
    ],
    [
      1280,
      720
    ],
    [
      1280,
      177
    ],
    [
      0,
      199
    ],
    [
      0,
      720
    ]
  ],
  "31.1": [
    [
      0,
      720
    ],
    [
      1280,
      720
    ],
    [
      1280,
      193
    ],
    [
      0,
      214
    ],
    [
      0,
      720
    ]
  ],
  "31.200000000000003": [
    [
      0,
      720
    ],
    [
      1280,
      720
    ],
    [
      1280,
      175
    ],
    [
      0,
      233
    ],
    [
      0,
      720
    ]
  ],
  "31.3": [
    [
      0,
      720
    ],
    [
      1280,
      720
    ],
    [
      1280,
      185
    ],
    [
      0,
      208
    ],
    [
      0,
      720
    ]
  ],
  "31.400000000000002": [
    [
      0,
      720
    ],
    [
      1280,
      720
    ],
    [
      1280,
      183
    ],
    [
      0,
      217
    ],
    [
      0,
      720
    ]
  ],
  "31.5": [
    [
      0,
      720
    ],
    [
      1280,
      720
    ],
    [
      1280,
      200
    ],
    [
      0,
      229
    ],
    [
      0,
      720
    ]
  ],
  "31.6": [
    [
      0,
      720
    ],
    [
      1280,
      720
    ],
    [
      1280,
      248
    ],
    [
      0,
      275
    ],
    [
      0,
      720
    ]
  ],
  "31.700000000000003": [
    [
      0,
      720
    ],
    [
      1280,
      720
    ],
    [
      1280,
      198
    ],
    [
      0,
      202
    ],
    [
      0,
      720
    ]
  ],
  "31.8": [
    [
      0,
      720
    ],
    [
      1280,
      720
    ],
    [
      1280,
      172
    ],
    [
      0,
      206
    ],
    [
      0,
      720
    ]
  ],
  "31.900000000000002": [
    [
      0,
      720
    ],
    [
      1280,
      720
    ],
    [
      1280,
      214
    ],
    [
      0,
      250
    ],
    [
      0,
      720
    ]
  ],
  "32.0": [
    [
      0,
      720
    ],
    [
      1280,
      720
    ],
    [
      1280,
      200
    ],
    [
      0,
      225
    ],
    [
      0,
      720
    ]
  ],
  "32.1": [
    [
      0,
      720
    ],
    [
      1280,
      720
    ],
    [
      1280,
      196
    ],
    [
      0,
      196
    ],
    [
      0,
      720
    ]
  ],
  "32.2": [
    [
      0,
      720
    ],
    [
      1280,
      720
    ],
    [
      1280,
      186
    ],
    [
      0,
      221
    ],
    [
      0,
      720
    ]
  ],
  "32.300000000000004": [
    [
      0,
      720
    ],
    [
      1280,
      720
    ],
    [
      1280,
      180
    ],
    [
      0,
      207
    ],
    [
      0,
      720
    ]
  ],
  "32.4": [
    [
      0,
      720
    ],
    [
      1280,
      720
    ],
    [
      1280,
      158
    ],
    [
      0,
      155
    ],
    [
      0,
      720
    ]
  ],
  "32.5": [
    [
      0,
      720
    ],
    [
      1280,
      720
    ],
    [
      1280,
      193
    ],
    [
      0,
      200
    ],
    [
      0,
      720
    ]
  ],
  "32.6": [
    [
      0,
      720
    ],
    [
      1280,
      720
    ],
    [
      1280,
      203
    ],
    [
      0,
      238
    ],
    [
      0,
      720
    ]
  ],
  "32.7": [
    [
      0,
      720
    ],
    [
      1280,
      720
    ],
    [
      1280,
      185
    ],
    [
      0,
      198
    ],
    [
      0,
      720
    ]
  ],
  "32.800000000000004": [
    [
      0,
      720
    ],
    [
      1280,
      720
    ],
    [
      1280,
      184
    ],
    [
      0,
      192
    ],
    [
      0,
      720
    ]
  ],
  "32.9": [
    [
      0,
      720
    ],
    [
      1280,
      720
    ],
    [
      1280,
      204
    ],
    [
      0,
      193
    ],
    [
      0,
      720
    ]
  ],
  "33.0": [
    [
      0,
      720
    ],
    [
      1280,
      720
    ],
    [
      1280,
      188
    ],
    [
      0,
      176
    ],
    [
      0,
      720
    ]
  ],
  "33.1": [
    [
      0,
      720
    ],
    [
      1280,
      720
    ],
    [
      1280,
      244
    ],
    [
      0,
      235
    ],
    [
      0,
      720
    ]
  ],
  "33.2": [
    [
      0,
      720
    ],
    [
      1280,
      720
    ],
    [
      1280,
      216
    ],
    [
      0,
      233
    ],
    [
      0,
      720
    ]
  ],
  "33.300000000000004": [
    [
      0,
      720
    ],
    [
      1280,
      720
    ],
    [
      1280,
      183
    ],
    [
      0,
      204
    ],
    [
      0,
      720
    ]
  ],
  "33.4": [
    [
      0,
      720
    ],
    [
      1280,
      720
    ],
    [
      1280,
      205
    ],
    [
      0,
      174
    ],
    [
      0,
      720
    ]
  ],
  "33.5": [
    [
      0,
      720
    ],
    [
      1280,
      720
    ],
    [
      1280,
      209
    ],
    [
      0,
      180
    ],
    [
      0,
      720
    ]
  ],
  "33.6": [
    [
      0,
      720
    ],
    [
      1280,
      720
    ],
    [
      1280,
      208
    ],
    [
      0,
      181
    ],
    [
      0,
      720
    ]
  ],
  "33.7": [
    [
      0,
      720
    ],
    [
      1280,
      720
    ],
    [
      1280,
      187
    ],
    [
      0,
      176
    ],
    [
      0,
      720
    ]
  ],
  "33.800000000000004": [
    [
      0,
      720
    ],
    [
      1280,
      720
    ],
    [
      1280,
      162
    ],
    [
      0,
      161
    ],
    [
      0,
      720
    ]
  ],
  "33.9": [
    [
      0,
      720
    ],
    [
      1280,
      720
    ],
    [
      1280,
      224
    ],
    [
      0,
      218
    ],
    [
      0,
      720
    ]
  ],
  "34.0": [
    [
      0,
      720
    ],
    [
      1280,
      720
    ],
    [
      1280,
      188
    ],
    [
      0,
      194
    ],
    [
      0,
      720
    ]
  ],
  "34.1": [
    [
      0,
      720
    ],
    [
      1280,
      720
    ],
    [
      1280,
      205
    ],
    [
      0,
      171
    ],
    [
      0,
      720
    ]
  ],
  "34.2": [
    [
      0,
      720
    ],
    [
      1280,
      720
    ],
    [
      1280,
      180
    ],
    [
      0,
      211
    ],
    [
      0,
      720
    ]
  ],
  "34.300000000000004": [
    [
      0,
      720
    ],
    [
      1280,
      720
    ],
    [
      1280,
      195
    ],
    [
      0,
      201
    ],
    [
      0,
      720
    ]
  ],
  "34.4": [
    [
      0,
      720
    ],
    [
      1280,
      720
    ],
    [
      1280,
      209
    ],
    [
      0,
      192
    ],
    [
      0,
      720
    ]
  ],
  "34.5": [
    [
      0,
      720
    ],
    [
      1280,
      720
    ],
    [
      1280,
      189
    ],
    [
      0,
      199
    ],
    [
      0,
      720
    ]
  ],
  "34.6": [
    [
      0,
      720
    ],
    [
      1280,
      720
    ],
    [
      1280,
      195
    ],
    [
      0,
      186
    ],
    [
      0,
      720
    ]
  ],
  "34.7": [
    [
      0,
      720
    ],
    [
      1280,
      720
    ],
    [
      1280,
      213
    ],
    [
      0,
      162
    ],
    [
      0,
      720
    ]
  ],
  "34.800000000000004": [
    [
      0,
      720
    ],
    [
      1280,
      720
    ],
    [
      1280,
      211
    ],
    [
      0,
      173
    ],
    [
      0,
      720
    ]
  ],
  "34.9": [
    [
      0,
      720
    ],
    [
      1280,
      720
    ],
    [
      1280,
      243
    ],
    [
      0,
      216
    ],
    [
      0,
      720
    ]
  ],
  "35.0": [
    [
      0,
      720
    ],
    [
      1280,
      720
    ],
    [
      1280,
      175
    ],
    [
      0,
      182
    ],
    [
      0,
      720
    ]
  ],
  "35.1": [
    [
      0,
      720
    ],
    [
      1280,
      720
    ],
    [
      1280,
      201
    ],
    [
      0,
      180
    ],
    [
      0,
      720
    ]
  ],
  "35.2": [
    [
      0,
      720
    ],
    [
      1280,
      720
    ],
    [
      1280,
      209
    ],
    [
      0,
      182
    ],
    [
      0,
      720
    ]
  ],
  "35.300000000000004": [
    [
      0,
      720
    ],
    [
      1280,
      720
    ],
    [
      1280,
      183
    ],
    [
      0,
      190
    ],
    [
      0,
      720
    ]
  ],
  "35.4": [
    [
      0,
      720
    ],
    [
      1280,
      720
    ],
    [
      1280,
      238
    ],
    [
      0,
      148
    ],
    [
      0,
      720
    ]
  ],
  "35.5": [
    [
      0,
      720
    ],
    [
      1280,
      720
    ],
    [
      1280,
      230
    ],
    [
      0,
      193
    ],
    [
      0,
      720
    ]
  ],
  "35.6": [
    [
      0,
      720
    ],
    [
      1280,
      720
    ],
    [
      1280,
      153
    ],
    [
      0,
      136
    ],
    [
      0,
      720
    ]
  ],
  "35.7": [
    [
      0,
      720
    ],
    [
      1280,
      720
    ],
    [
      1280,
      205
    ],
    [
      0,
      153
    ],
    [
      0,
      720
    ]
  ],
  "35.800000000000004": [
    [
      0,
      720
    ],
    [
      1280,
      720
    ],
    [
      1280,
      175
    ],
    [
      0,
      120
    ],
    [
      0,
      720
    ]
  ],
  "35.9": [
    [
      1280,
      350
    ],
    [
      0,
      278
    ],
    [
      0,
      372
    ],
    [
      1280,
      363
    ],
    [
      1280,
      350
    ]
  ],
  "36.0": [
    [
      0,
      720
    ],
    [
      1280,
      720
    ],
    [
      1280,
      288
    ],
    [
      0,
      262
    ],
    [
      0,
      720
    ]
  ],
  "36.1": [
    [
      0,
      720
    ],
    [
      1280,
      720
    ],
    [
      1280,
      276
    ],
    [
      0,
      258
    ],
    [
      0,
      720
    ]
  ],
  "36.2": [
    [
      0,
      720
    ],
    [
      1280,
      720
    ],
    [
      1280,
      306
    ],
    [
      0,
      292
    ],
    [
      0,
      720
    ]
  ],
  "36.300000000000004": [
    [
      1280,
      372
    ],
    [
      0,
      346
    ],
    [
      0,
      659
    ],
    [
      1280,
      663
    ],
    [
      1280,
      372
    ]
  ],
  "36.4": [
    [
      0,
      720
    ],
    [
      1280,
      720
    ],
    [
      1280,
      217
    ],
    [
      0,
      224
    ],
    [
      0,
      720
    ]
  ],
  "36.5": [
    [
      0,
      720
    ],
    [
      1280,
      720
    ],
    [
      1280,
      124
    ],
    [
      0,
      90
    ],
    [
      0,
      720
    ]
  ],
  "36.6": [
    [
      1280,
      241
    ],
    [
      0,
      230
    ],
    [
      0,
      720
    ],
    [
      1133,
      720
    ],
    [
      1280,
      719
    ],
    [
      1280,
      241
    ]
  ],
  "36.7": [
    [
      1280,
      339
    ],
    [
      0,
      342
    ],
    [
      0,
      668
    ],
    [
      1280,
      692
    ],
    [
      1280,
      339
    ]
  ],
  "36.800000000000004": [
    [
      1280,
      344
    ],
    [
      0,
      336
    ],
    [
      0,
      636
    ],
    [
      1280,
      621
    ],
    [
      1280,
      344
    ]
  ],
  "36.9": [
    [
      1280,
      0
    ],
    [
      746,
      0
    ],
    [
      0,
      100
    ],
    [
      0,
      658
    ],
    [
      1280,
      629
    ],
    [
      1280,
      0
    ]
  ],
  "37.0": [
    [
      1280,
      335
    ],
    [
      0,
      330
    ],
    [
      0,
      679
    ],
    [
      1280,
      670
    ],
    [
      1280,
      335
    ]
  ],
  "37.1": [
    [
      1280,
      153
    ],
    [
      0,
      162
    ],
    [
      0,
      657
    ],
    [
      1280,
      643
    ],
    [
      1280,
      153
    ]
  ],
  "37.2": [
    [
      1280,
      347
    ],
    [
      0,
      364
    ],
    [
      0,
      599
    ],
    [
      1280,
      642
    ],
    [
      1280,
      347
    ]
  ],
  "37.300000000000004": [
    [
      1280,
      257
    ],
    [
      0,
      302
    ],
    [
      0,
      368
    ],
    [
      1085,
      384
    ],
    [
      1280,
      408
    ],
    [
      1280,
      257
    ]
  ],
  "37.4": [
    [
      1280,
      402
    ],
    [
      1028,
      390
    ],
    [
      0,
      396
    ],
    [
      0,
      605
    ],
    [
      1280,
      584
    ],
    [
      1280,
      402
    ]
  ],
  "37.5": [
    [
      1280,
      720
    ],
    [
      1280,
      223
    ],
    [
      0,
      219
    ],
    [
      0,
      690
    ],
    [
      724,
      720
    ],
    [
      1280,
      720
    ]
  ],
  "37.6": [
    [
      1280,
      232
    ],
    [
      0,
      207
    ],
    [
      0,
      698
    ],
    [
      1280,
      668
    ],
    [
      1280,
      232
    ]
  ],
  "37.7": [
    [
      0,
      720
    ],
    [
      1280,
      720
    ],
    [
      1280,
      96
    ],
    [
      0,
      99
    ],
    [
      0,
      720
    ]
  ],
  "37.800000000000004": [
    [
      1280,
      358
    ],
    [
      0,
      356
    ],
    [
      0,
      627
    ],
    [
      1280,
      649
    ],
    [
      1280,
      358
    ]
  ],
  "37.9": [
    [
      1280,
      321
    ],
    [
      0,
      329
    ],
    [
      0,
      683
    ],
    [
      1280,
      669
    ],
    [
      1280,
      321
    ]
  ],
  "38.0": [
    [
      1280,
      350
    ],
    [
      0,
      298
    ],
    [
      0,
      668
    ],
    [
      1280,
      633
    ],
    [
      1280,
      350
    ]
  ],
  "38.1": [
    [
      1280,
      351
    ],
    [
      0,
      329
    ],
    [
      0,
      661
    ],
    [
      1280,
      623
    ],
    [
      1280,
      351
    ]
  ],
  "38.2": [
    [
      0,
      720
    ],
    [
      1280,
      720
    ],
    [
      1280,
      164
    ],
    [
      139,
      109
    ],
    [
      0,
      168
    ],
    [
      0,
      720
    ]
  ],
  "38.300000000000004": [
    [
      0,
      720
    ],
    [
      1280,
      720
    ],
    [
      1280,
      153
    ],
    [
      156,
      117
    ],
    [
      0,
      184
    ],
    [
      0,
      720
    ]
  ],
  "38.400000000000006": [
    [
      0,
      720
    ],
    [
      1280,
      720
    ],
    [
      1280,
      160
    ],
    [
      164,
      116
    ],
    [
      0,
      190
    ],
    [
      0,
      720
    ]
  ],
  "38.5": [
    [
      0,
      720
    ],
    [
      1280,
      720
    ],
    [
      1280,
      179
    ],
    [
      155,
      124
    ],
    [
      0,
      187
    ],
    [
      0,
      720
    ]
  ],
  "38.6": [
    [
      0,
      720
    ],
    [
      1280,
      720
    ],
    [
      1280,
      189
    ],
    [
      189,
      121
    ],
    [
      0,
      194
    ],
    [
      0,
      720
    ]
  ],
  "38.7": [
    [
      0,
      720
    ],
    [
      1280,
      720
    ],
    [
      1280,
      150
    ],
    [
      207,
      108
    ],
    [
      0,
      201
    ],
    [
      0,
      720
    ]
  ],
  "38.800000000000004": [
    [
      0,
      720
    ],
    [
      1280,
      720
    ],
    [
      1280,
      162
    ],
    [
      221,
      117
    ],
    [
      0,
      213
    ],
    [
      0,
      720
    ]
  ],
  "38.900000000000006": [
    [
      0,
      720
    ],
    [
      1280,
      720
    ],
    [
      1280,
      166
    ],
    [
      235,
      119
    ],
    [
      0,
      219
    ],
    [
      0,
      720
    ]
  ],
  "39.0": [
    [
      0,
      720
    ],
    [
      1280,
      720
    ],
    [
      1280,
      129
    ],
    [
      239,
      112
    ],
    [
      0,
      229
    ],
    [
      0,
      720
    ]
  ],
  "39.1": [
    [
      0,
      720
    ],
    [
      1280,
      720
    ],
    [
      1280,
      156
    ],
    [
      271,
      137
    ],
    [
      0,
      262
    ],
    [
      0,
      720
    ]
  ],
  "39.2": [
    [
      0,
      720
    ],
    [
      1280,
      720
    ],
    [
      1280,
      154
    ],
    [
      254,
      158
    ],
    [
      0,
      272
    ],
    [
      0,
      720
    ]
  ],
  "39.300000000000004": [
    [
      0,
      720
    ],
    [
      1280,
      720
    ],
    [
      1280,
      153
    ],
    [
      309,
      129
    ],
    [
      0,
      273
    ],
    [
      0,
      720
    ]
  ],
  "39.400000000000006": [
    [
      1280,
      720
    ],
    [
      1280,
      240
    ],
    [
      236,
      215
    ],
    [
      0,
      304
    ],
    [
      0,
      694
    ],
    [
      288,
      720
    ],
    [
      1280,
      720
    ]
  ],
  "39.5": [
    [
      0,
      720
    ],
    [
      1280,
      720
    ],
    [
      1280,
      162
    ],
    [
      305,
      127
    ],
    [
      0,
      267
    ],
    [
      0,
      720
    ]
  ],
  "39.6": [
    [
      0,
      720
    ],
    [
      1280,
      720
    ],
    [
      1280,
      165
    ],
    [
      326,
      136
    ],
    [
      0,
      265
    ],
    [
      0,
      720
    ]
  ],
  "39.7": [
    [
      1280,
      720
    ],
    [
      1280,
      295
    ],
    [
      260,
      256
    ],
    [
      0,
      325
    ],
    [
      0,
      718
    ],
    [
      26,
      720
    ],
    [
      1280,
      720
    ]
  ],
  "39.800000000000004": [
    [
      0,
      720
    ],
    [
      1280,
      720
    ],
    [
      1280,
      145
    ],
    [
      372,
      121
    ],
    [
      0,
      290
    ],
    [
      0,
      720
    ]
  ],
  "39.900000000000006": [
    [
      0,
      720
    ],
    [
      1280,
      720
    ],
    [
      1280,
      166
    ],
    [
      360,
      124
    ],
    [
      0,
      267
    ],
    [
      0,
      720
    ]
  ],
  "40.0": [
    [
      0,
      720
    ],
    [
      1280,
      720
    ],
    [
      1280,
      166
    ],
    [
      393,
      148
    ],
    [
      0,
      326
    ],
    [
      0,
      720
    ]
  ],
  "40.1": [
    [
      0,
      720
    ],
    [
      1280,
      720
    ],
    [
      1280,
      168
    ],
    [
      414,
      151
    ],
    [
      0,
      328
    ],
    [
      0,
      720
    ]
  ],
  "40.2": [
    [
      0,
      720
    ],
    [
      1280,
      720
    ],
    [
      1280,
      166
    ],
    [
      421,
      123
    ],
    [
      0,
      311
    ],
    [
      0,
      720
    ]
  ],
  "40.300000000000004": [
    [
      0,
      720
    ],
    [
      1280,
      720
    ],
    [
      1280,
      173
    ],
    [
      437,
      165
    ],
    [
      0,
      358
    ],
    [
      0,
      720
    ]
  ],
  "40.400000000000006": [
    [
      0,
      720
    ],
    [
      1280,
      720
    ],
    [
      1280,
      163
    ],
    [
      453,
      132
    ],
    [
      0,
      324
    ],
    [
      0,
      720
    ]
  ],
  "40.5": [
    [
      0,
      720
    ],
    [
      1280,
      720
    ],
    [
      1280,
      170
    ],
    [
      460,
      136
    ],
    [
      0,
      328
    ],
    [
      0,
      720
    ]
  ],
  "40.6": [
    [
      0,
      720
    ],
    [
      1280,
      720
    ],
    [
      1280,
      165
    ],
    [
      480,
      135
    ],
    [
      0,
      333
    ],
    [
      0,
      720
    ]
  ],
  "40.7": [
    [
      0,
      720
    ],
    [
      1280,
      720
    ],
    [
      1280,
      148
    ],
    [
      502,
      117
    ],
    [
      0,
      344
    ],
    [
      0,
      720
    ]
  ],
  "40.800000000000004": [
    [
      0,
      720
    ],
    [
      1280,
      720
    ],
    [
      1280,
      118
    ],
    [
      511,
      120
    ],
    [
      0,
      354
    ],
    [
      0,
      720
    ]
  ],
  "40.900000000000006": [
    [
      0,
      720
    ],
    [
      1280,
      720
    ],
    [
      1280,
      161
    ],
    [
      481,
      149
    ],
    [
      0,
      356
    ],
    [
      0,
      720
    ]
  ],
  "41.0": [
    [
      0,
      720
    ],
    [
      1280,
      720
    ],
    [
      1280,
      259
    ],
    [
      419,
      247
    ],
    [
      0,
      404
    ],
    [
      0,
      720
    ]
  ],
  "41.1": [
    [
      0,
      720
    ],
    [
      1280,
      720
    ],
    [
      1280,
      165
    ],
    [
      490,
      143
    ],
    [
      0,
      341
    ],
    [
      0,
      720
    ]
  ],
  "41.2": [
    [
      0,
      720
    ],
    [
      1280,
      720
    ],
    [
      1280,
      169
    ],
    [
      535,
      127
    ],
    [
      0,
      362
    ],
    [
      0,
      720
    ]
  ],
  "41.300000000000004": [
    [
      0,
      720
    ],
    [
      1280,
      720
    ],
    [
      1280,
      132
    ],
    [
      516,
      129
    ],
    [
      0,
      373
    ],
    [
      0,
      720
    ]
  ],
  "41.400000000000006": [
    [
      0,
      720
    ],
    [
      1280,
      720
    ],
    [
      1280,
      164
    ],
    [
      494,
      139
    ],
    [
      0,
      358
    ],
    [
      0,
      720
    ]
  ],
  "41.5": [
    [
      0,
      720
    ],
    [
      1280,
      720
    ],
    [
      1280,
      171
    ],
    [
      512,
      131
    ],
    [
      0,
      358
    ],
    [
      0,
      720
    ]
  ],
  "41.6": [
    [
      0,
      720
    ],
    [
      1280,
      720
    ],
    [
      1280,
      191
    ],
    [
      516,
      134
    ],
    [
      0,
      357
    ],
    [
      0,
      720
    ]
  ]
}